fapis/README.md
fapis/cli.py
fapis/templates/infrastructure/base/.env.example
fapis/templates/infrastructure/base/.gitignore
fapis/templates/infrastructure/base/CONTRIBUTING.md
fapis/templates/infrastructure/base/Dockerfile
fapis/templates/infrastructure/base/LICENSE
fapis/templates/infrastructure/base/Makefile
fapis/templates/infrastructure/base/README.md
fapis/templates/infrastructure/base/pytest.ini
fapis/templates/infrastructure/base/requirements.txt
fapis/templates/infrastructure/base/.pytest_cache/.gitignore
fapis/templates/infrastructure/base/.pytest_cache/CACHEDIR.TAG
fapis/templates/infrastructure/base/.pytest_cache/README.md
fapis/templates/infrastructure/base/.pytest_cache/v/cache/lastfailed
fapis/templates/infrastructure/base/.pytest_cache/v/cache/nodeids
fapis/templates/infrastructure/base/app/__init__.py
fapis/templates/infrastructure/base/app/main.py
fapis/templates/infrastructure/base/app/api/__init__.py
fapis/templates/infrastructure/base/app/api/health.py
fapis/templates/infrastructure/base/app/core/__init__.py
fapis/templates/infrastructure/base/app/core/config.py
fapis/templates/infrastructure/base/tests/test_health.py
fapis-0.1.1.dist-info/licenses/LICENSE
fapis-0.1.1.dist-info/METADATA
fapis-0.1.1.dist-info/WHEEL
fapis-0.1.1.dist-info/entry_points.txt
fapis-0.1.1.dist-info/top_level.txt
fapis-0.1.1.dist-info/RECORD
