Metadata-Version: 2.4
Name: fapis
Version: 0.1.1
Summary: FastAPI infrastructure starter CLI
Author-email: Webi Muleta <webimuleta01@gmail.com>
License: MIT
Project-URL: Homepage, https://github.com/Dirac1235/fapis
Project-URL: Repository, https://github.com/Dirac1235/fapis
Project-URL: PyPI, https://pypi.org/project/fapis/
Keywords: fastapi,infrastructure,template,cli
Classifier: Development Status :: 3 - Alpha
Classifier: Intended Audience :: Developers
Classifier: License :: OSI Approved :: MIT License
Classifier: Programming Language :: Python :: 3
Classifier: Programming Language :: Python :: 3.9
Classifier: Framework :: FastAPI
Requires-Python: >=3.9
License-File: LICENSE
Requires-Dist: click
Dynamic: license-file
